easyuri/__init__.py
easyuri-0.1.4.dist-info/METADATA
easyuri-0.1.4.dist-info/WHEEL
easyuri-0.1.4.dist-info/RECORD
