Metadata-Version: 2.1
Name: easyuri
Version: 0.1.4
Summary: a dumb URL parser with a smart interface
Home-page: https://ragt.ag/code/projects/easyuri
License: BSD-2-Clause
Keywords: web,www
Author: Angelo Gladding
Author-email: angelo@ragt.ag
Requires-Python: >=3.8,<3.11
Classifier: License :: OSI Approved :: BSD License
Classifier: Programming Language :: Python :: 3
Classifier: Programming Language :: Python :: 3.8
Classifier: Programming Language :: Python :: 3.9
Classifier: Programming Language :: Python :: 3.10
Requires-Dist: hstspreload (>=2023.1.1,<2024.0.0)
Requires-Dist: requests (>=2.28.2,<3.0.0)
Project-URL: Documentation, https://ragt.ag/code/projects/easyuri/api
Project-URL: Repository, https://ragt.ag/code/projects/easyuri.git
